krezi/__init__.py
krezi/common.py
krezi/cover_letter_generator_util/__init__.py
krezi/cover_letter_generator_util/automated_cover_letter_generator.py
krezi/email_util/__init__.py
krezi/email_util/email_notifier.py
krezi/logging_util/__init__.py
krezi/logging_util/file_logger.py
krezi/mssql_util/__init__.py
krezi/mssql_util/pymssql_dao.py
krezi/multiprocessing_util/__init__.py
krezi/multiprocessing_util/mp_class_util.py
krezi/multiprocessing_util/mp_util.py
krezi/posgresql_util/__init__.py
krezi/posgresql_util/posgresql_util.py
krezi/stopwatch_util/__init__.py
krezi/stopwatch_util/stopwatch.py
krezi-1.5.dist-info/LICENSE
krezi-1.5.dist-info/METADATA
krezi-1.5.dist-info/WHEEL
krezi-1.5.dist-info/top_level.txt
krezi-1.5.dist-info/RECORD
