Metadata-Version: 2.1
Name: krezi
Version: 1.5
Summary: Array of Utilities for Lazy but Efficient Programmers
Author: Aadil Zikre
Author-email: aadilzikre@gmail.com
License: UNKNOWN
Platform: UNKNOWN
Classifier: Development Status :: 4 - Beta
Classifier: License :: OSI Approved :: MIT License
Classifier: Operating System :: OS Independent
Classifier: Programming Language :: Python :: 3
Requires-Python: >= 3.9
License-File: LICENSE
Requires-Dist: numpy (>=1.23.0)
Requires-Dist: pandas (>=1.4.2)
Requires-Dist: itables (>=1.5.2)
Requires-Dist: tqdm
